Metadata-Version: 1.1
Name: django-templated-email-fork
Version: 0.4.10
Summary: A Django oriented templated / transaction email abstraction
Home-page: https://github.com/vintasoftware/django-templated-email-fork
Author: Andre Ericson
Author-email: andre@vinta.com.br
License: MIT
Platform: any
Classifier: Development Status :: 5 - Production/Stable
Classifier: Intended Audience :: Developers
Classifier: License :: OSI Approved :: MIT License
Classifier: Operating System :: OS Independent
Classifier: Programming Language :: Python
Classifier: Topic :: Software Development :: Libraries :: Python Modules
Classifier: Framework :: Django
